JunkOrganizer.py
junk_organizer-0.0.1.dist-info/METADATA
junk_organizer-0.0.1.dist-info/WHEEL
junk_organizer-0.0.1.dist-info/top_level.txt
junk_organizer-0.0.1.dist-info/RECORD
